lingo/__init__.py
lingo/cli.py
lingo/core.py
lingo/models.py
lingo/preprocessing.py
lingo/py.typed
lingo/setup_utils.py
lingo/utils.py
lingo/configs/default.yaml
lingo_nlp_toolkit-2.3.dist-info/LICENSE
lingo_nlp_toolkit-2.3.dist-info/METADATA
lingo_nlp_toolkit-2.3.dist-info/WHEEL
lingo_nlp_toolkit-2.3.dist-info/entry_points.txt
lingo_nlp_toolkit-2.3.dist-info/top_level.txt
lingo_nlp_toolkit-2.3.dist-info/RECORD
